{
  "id": "lab_statistical_arbitrage_20260304_020359_798911_m4",
  "name": "lab_statistical_arbitrage_20260304_020359_798911_m4",
  "strategy_type": "statistical_arbitrage",
  "category": "statistical_arbitrage",
  "family": "statistical_arbitrage",
  "asset_class": "indices",
  "timeframe": "1d",
  "indicators": [
    "vwap",
    "zscore",
    "bollinger"
  ],
  "entry_logic": "zscore_extreme AND spread_reversion_signal",
  "exit_logic": "mean_reversion_completed OR stop_loss",
  "risk_model": "fixed_risk",
  "parameters": {
    "ema_fast": 15,
    "ema_slow": 24.6401,
    "rsi_length": 10.5947,
    "atr_length": 18.2078,
    "atr_stop_mult": 3.2223,
    "risk_multiple": 2.3317,
    "volume_filter_mult": 1.7573,
    "zscore_entry": 2.2043,
    "zscore_exit": 1.0167
  },
  "stage": "RESEARCH",
  "active": false,
  "metadata": {
    "created_at": "2026-03-04T02:03:59Z",
    "mutation_origin": "lab_statistical_arbitrage_20260304_020359_798911"
  },
  "strategy_name": "lab_statistical_arbitrage_20260304_020359_798911_m4",
  "creation_date": "2026-03-04T02:03:59Z",
  "indicators_used": [
    "vwap",
    "zscore",
    "bollinger"
  ],
  "performance_metrics": {},
  "mutation_origin": "lab_statistical_arbitrage_20260304_020359_798911"
}