{
  "id": "lab_momentum_20260303_162821_466709_m4",
  "name": "lab_momentum_20260303_162821_466709_m4",
  "strategy_type": "momentum",
  "category": "momentum",
  "family": "momentum",
  "asset_class": "crypto",
  "timeframe": "1d",
  "indicators": [
    "stochastic",
    "macd",
    "ema"
  ],
  "entry_logic": "ema_fast_cross_ema_slow AND atr_filter",
  "exit_logic": "trailing_atr_stop OR ema_reversal",
  "risk_model": "atr_risk",
  "parameters": {
    "ema_fast": 7.4129,
    "ema_slow": 25.5716,
    "rsi_length": 9.7802,
    "atr_length": 13.5245,
    "atr_stop_mult": 4.0222,
    "risk_multiple": 1.2645,
    "volume_filter_mult": 1.024
  },
  "stage": "RESEARCH",
  "active": false,
  "metadata": {
    "created_at": "2026-03-03T16:28:21Z",
    "mutation_origin": "lab_momentum_20260303_162821_466709"
  },
  "metrics": {
    "win_rate": 52.6087,
    "expectancy": 0.0331,
    "avg_win": 0.7563,
    "avg_loss": 0.7697,
    "expectancy_rolling_100": 0.1237,
    "max_dd": 11.0809,
    "profit_factor": 1.0907,
    "sharpe": 0.5972,
    "returns": [
      -0.012485,
      -0.009229,
      0.013261,
      0.00066,
      0.001859,
      -0.002303,
      -0.012632,
      0.008127,
      -0.013559,
      0.003957,
      0.009727,
      -0.002354,
      0.008058,
      0.00442,
      -0.012984,
      0.003324,
      0.002809,
      0.004366,
      -0.008777,
      -0.006708,
      0.003283,
      -0.006524,
      0.004263,
      -0.002963,
      0.005643,
      0.010574,
      -0.000921,
      -0.000102,
      -0.011348,
      -6.6e-05,
      -0.012578,
      0.007702,
      0.009789,
      -0.010093,
      0.001498,
      -0.004292,
      0.011689,
      -0.011745,
      -0.004748,
      -0.002137,
      0.013346,
      -0.014448,
      0.004359,
      0.009875,
      0.010148,
      -0.003401,
      0.002028,
      -0.011537,
      0.007344,
      -0.00618,
      -0.012896,
      -0.002506,
      0.01216,
      0.006705,
      -0.014401,
      0.004533,
      -0.004001,
      -0.004941,
      -0.002453,
      -0.014144,
      0.009356,
      -0.007404,
      -0.00577,
      0.012896,
      -0.006171,
      0.005734,
      0.00301,
      -0.014946,
      0.007766,
      -0.009906,
      0.011505,
      0.004337,
      0.00151,
      -0.009603,
      -0.010082,
      0.009398,
      0.009454,
      -0.008792,
      -0.002274,
      -0.006308,
      0.009116,
      -0.011603,
      -0.001984,
      -0.0116,
      0.013864,
      -0.004177,
      0.004314,
      -0.007902,
      0.01339,
      -0.004015,
      -0.012903,
      0.002405,
      -0.003291,
      -0.002979,
      0.008094,
      0.012868,
      0.001092,
      0.01199,
      0.006852,
      -0.000255,
      0.000658,
      0.003046,
      -0.013538,
      -0.012745,
      -0.004805,
      -0.012792,
      -0.00656,
      0.014088,
      0.001212,
      -4e-05,
      0.005832,
      0.003997,
      -0.001593,
      0.012062,
      0.003124,
      0.007687,
      -0.004633,
      0.014974,
      0.008344,
      0.008792,
      0.009961,
      -0.001211,
      0.003544,
      -0.014349,
      -0.00293,
      0.01196,
      -0.012207,
      0.000924,
      0.009402,
      0.008199,
      0.013594,
      -0.01321,
      0.001433,
      -0.004849,
      0.007357,
      0.006971,
      0.006382,
      0.002675,
      0.011028,
      0.001609,
      -0.010997,
      0.00071,
      0.004071,
      0.011004,
      -0.002227,
      -0.007162,
      0.013258,
      0.012038,
      0.002679,
      0.004218,
      0.00322,
      0.007147,
      0.014924,
      0.01046,
      -0.008067,
      0.009344,
      -0.013643,
      -0.006683,
      0.008713,
      -0.009892,
      -0.008485,
      -0.003762,
      0.005161,
      -0.002902,
      -0.006684,
      0.014525,
      -0.000815,
      0.007694,
      0.014297,
      0.014322,
      0.002516,
      -0.003487,
      -0.00919,
      -0.013476,
      0.007448,
      0.004655,
      0.012628,
      0.006681,
      -0.008083,
      0.00557,
      0.000855,
      -0.004242,
      -0.012772,
      0.00172,
      -0.002983,
      -0.01229,
      0.012585,
      -0.002248,
      -0.000372,
      0.004877,
      -0.012921,
      -0.004698,
      0.002111,
      0.01225,
      -0.007475,
      -0.003265,
      0.014935,
      -0.01456,
      -0.014422,
      0.011511
    ],
    "volatility": 0.008604,
    "sample_size": 200
  },
  "validation_reason": "profit_factor_below_threshold",
  "strategy_name": "lab_momentum_20260303_162821_466709_m4",
  "creation_date": "2026-03-03T16:28:21Z",
  "indicators_used": [
    "stochastic",
    "macd",
    "ema"
  ],
  "performance_metrics": {
    "win_rate": 52.6087,
    "expectancy": 0.0331,
    "avg_win": 0.7563,
    "avg_loss": 0.7697,
    "expectancy_rolling_100": 0.1237,
    "max_dd": 11.0809,
    "profit_factor": 1.0907,
    "sharpe": 0.5972,
    "returns": [
      -0.012485,
      -0.009229,
      0.013261,
      0.00066,
      0.001859,
      -0.002303,
      -0.012632,
      0.008127,
      -0.013559,
      0.003957,
      0.009727,
      -0.002354,
      0.008058,
      0.00442,
      -0.012984,
      0.003324,
      0.002809,
      0.004366,
      -0.008777,
      -0.006708,
      0.003283,
      -0.006524,
      0.004263,
      -0.002963,
      0.005643,
      0.010574,
      -0.000921,
      -0.000102,
      -0.011348,
      -6.6e-05,
      -0.012578,
      0.007702,
      0.009789,
      -0.010093,
      0.001498,
      -0.004292,
      0.011689,
      -0.011745,
      -0.004748,
      -0.002137,
      0.013346,
      -0.014448,
      0.004359,
      0.009875,
      0.010148,
      -0.003401,
      0.002028,
      -0.011537,
      0.007344,
      -0.00618,
      -0.012896,
      -0.002506,
      0.01216,
      0.006705,
      -0.014401,
      0.004533,
      -0.004001,
      -0.004941,
      -0.002453,
      -0.014144,
      0.009356,
      -0.007404,
      -0.00577,
      0.012896,
      -0.006171,
      0.005734,
      0.00301,
      -0.014946,
      0.007766,
      -0.009906,
      0.011505,
      0.004337,
      0.00151,
      -0.009603,
      -0.010082,
      0.009398,
      0.009454,
      -0.008792,
      -0.002274,
      -0.006308,
      0.009116,
      -0.011603,
      -0.001984,
      -0.0116,
      0.013864,
      -0.004177,
      0.004314,
      -0.007902,
      0.01339,
      -0.004015,
      -0.012903,
      0.002405,
      -0.003291,
      -0.002979,
      0.008094,
      0.012868,
      0.001092,
      0.01199,
      0.006852,
      -0.000255,
      0.000658,
      0.003046,
      -0.013538,
      -0.012745,
      -0.004805,
      -0.012792,
      -0.00656,
      0.014088,
      0.001212,
      -4e-05,
      0.005832,
      0.003997,
      -0.001593,
      0.012062,
      0.003124,
      0.007687,
      -0.004633,
      0.014974,
      0.008344,
      0.008792,
      0.009961,
      -0.001211,
      0.003544,
      -0.014349,
      -0.00293,
      0.01196,
      -0.012207,
      0.000924,
      0.009402,
      0.008199,
      0.013594,
      -0.01321,
      0.001433,
      -0.004849,
      0.007357,
      0.006971,
      0.006382,
      0.002675,
      0.011028,
      0.001609,
      -0.010997,
      0.00071,
      0.004071,
      0.011004,
      -0.002227,
      -0.007162,
      0.013258,
      0.012038,
      0.002679,
      0.004218,
      0.00322,
      0.007147,
      0.014924,
      0.01046,
      -0.008067,
      0.009344,
      -0.013643,
      -0.006683,
      0.008713,
      -0.009892,
      -0.008485,
      -0.003762,
      0.005161,
      -0.002902,
      -0.006684,
      0.014525,
      -0.000815,
      0.007694,
      0.014297,
      0.014322,
      0.002516,
      -0.003487,
      -0.00919,
      -0.013476,
      0.007448,
      0.004655,
      0.012628,
      0.006681,
      -0.008083,
      0.00557,
      0.000855,
      -0.004242,
      -0.012772,
      0.00172,
      -0.002983,
      -0.01229,
      0.012585,
      -0.002248,
      -0.000372,
      0.004877,
      -0.012921,
      -0.004698,
      0.002111,
      0.01225,
      -0.007475,
      -0.003265,
      0.014935,
      -0.01456,
      -0.014422,
      0.011511
    ],
    "volatility": 0.008604,
    "sample_size": 200
  },
  "mutation_origin": "lab_momentum_20260303_162821_466709"
}